medicine/__init__.py
medicine/logger.py
medicine/model.py
medicine/plotting.py
medicine/run.py
medicine_demos/__init__.py
medicine_demos/run_demo.py
medicine_demos/example_dataset/peak_amplitudes.npy
medicine_demos/example_dataset/peak_depths.npy
medicine_demos/example_dataset/peak_times.npy
medicine_neuro-1.6.dist-info/licenses/LICENSE
medicine_neuro-1.6.dist-info/METADATA
medicine_neuro-1.6.dist-info/WHEEL
medicine_neuro-1.6.dist-info/top_level.txt
medicine_neuro-1.6.dist-info/RECORD
