Metadata-Version: 2.4
Name: medicine-neuro
Version: 1.6
Summary: MEDiCINe: Motion Estimation by Distributional Contrastive Inference for Neurophysiology.
Author: Nick Watters
Author-email: nwatters@mit.edu
Maintainer-email: Nick Watters <nwatters@mit.edu>
License: MIT License
Project-URL: homepage, https://jazlab.github.io/medicine.github.io
Project-URL: documentation, https://jazlab.github.io/medicine.github.io
Project-URL: repository, https://github.com/jazlab/medicine.github.io
Project-URL: pypi, https://pypi.org/project/medicine-neuro
Keywords: neuroscience,neurophysiology,spike sorting,machine learning,motion,python
Classifier: Development Status :: 4 - Beta
Classifier: License :: OSI Approved :: MIT License
Classifier: Operating System :: OS Independent
Classifier: Programming Language :: Python :: 3
Classifier: Topic :: Scientific/Engineering
Requires-Python: >=3.9.6
License-File: LICENSE
Requires-Dist: torch>=2.5.0
Requires-Dist: seaborn>=0.13.2
Requires-Dist: scipy>=1.13.1
Requires-Dist: tqdm>=4.66.6
Dynamic: license-file
